odoo/addons/stock_production_lot_warranty/README.rst
odoo/addons/stock_production_lot_warranty/__init__.py
odoo/addons/stock_production_lot_warranty/__manifest__.py
odoo/addons/stock_production_lot_warranty/i18n/pt.po
odoo/addons/stock_production_lot_warranty/i18n/pt_BR.po
odoo/addons/stock_production_lot_warranty/i18n/stock_production_lot_warranty.pot
odoo/addons/stock_production_lot_warranty/models/__init__.py
odoo/addons/stock_production_lot_warranty/models/stock_production_lot.py
odoo/addons/stock_production_lot_warranty/readme/CONFIGURE.rst
odoo/addons/stock_production_lot_warranty/readme/CONTRIBUTORS.rst
odoo/addons/stock_production_lot_warranty/readme/CREDITS.rst
odoo/addons/stock_production_lot_warranty/readme/DESCRIPTION.rst
odoo/addons/stock_production_lot_warranty/readme/USAGE.rst
odoo/addons/stock_production_lot_warranty/static/description/icon.png
odoo/addons/stock_production_lot_warranty/static/description/index.html
odoo/addons/stock_production_lot_warranty/tests/__init__.py
odoo/addons/stock_production_lot_warranty/tests/test_product_lot_warranty.py
odoo/addons/stock_production_lot_warranty/views/stock_production_lot.xml
odoo_addon_stock_production_lot_warranty-15.0.1.1.0.2.dist-info/METADATA
odoo_addon_stock_production_lot_warranty-15.0.1.1.0.2.dist-info/WHEEL
odoo_addon_stock_production_lot_warranty-15.0.1.1.0.2.dist-info/top_level.txt
odoo_addon_stock_production_lot_warranty-15.0.1.1.0.2.dist-info/RECORD
