Metadata-Version: 2.1
Name: odoo-addon-stock-production-lot-warranty
Version: 15.0.1.1.0.2
Summary: Add warranty date to stock production lot
Home-page: https://github.com/OCA/rma
Author: Open Source Integrators, Odoo Community Association (OCA)
Author-email: support@odoo-community.org
License: AGPL-3
Platform: UNKNOWN
Classifier: Programming Language :: Python
Classifier: Framework :: Odoo
Classifier: Framework :: Odoo :: 15.0
Classifier: License :: OSI Approved :: GNU Affero General Public License v3
Classifier: Development Status :: 4 - Beta
Requires-Python: >=3.8
Requires-Dist: odoo-addon-product-warranty <15.1dev,>=15.0dev
Requires-Dist: odoo <15.1dev,>=15.0a
